animaid/__init__.py
animaid/animate.py
animaid/animate_server.py
animaid/css_types.py
animaid/html_button.py
animaid/html_checkbox.py
animaid/html_dict.py
animaid/html_float.py
animaid/html_input.py
animaid/html_int.py
animaid/html_list.py
animaid/html_object.py
animaid/html_select.py
animaid/html_set.py
animaid/html_slider.py
animaid/html_string.py
animaid/html_text_input.py
animaid/html_tuple.py
animaid/input_event.py
animaid/py.typed
animaid/cli/__init__.py
animaid/cli/demo.py
animaid/cli/tutorial.py
animaid/containers/__init__.py
animaid/containers/base.py
animaid/containers/card.py
animaid/containers/column.py
animaid/containers/divider.py
animaid/containers/row.py
animaid/containers/spacer.py
animaid-0.5.0.dist-info/METADATA
animaid-0.5.0.dist-info/WHEEL
animaid-0.5.0.dist-info/entry_points.txt
animaid-0.5.0.dist-info/licenses/LICENSE
animaid-0.5.0.dist-info/RECORD
