Metadata-Version: 2.4
Name: animaid
Version: 0.5.0
Summary: A GUI toolkit for animating Python data structures
Project-URL: Homepage, https://github.com/jdrumgoole/animaid
Project-URL: Documentation, https://animaid.readthedocs.io
Project-URL: Repository, https://github.com/jdrumgoole/animaid
Project-URL: Issues, https://github.com/jdrumgoole/animaid/issues
Author-email: Joe Drumgoole <joe@joedrumgoole.com>
License-Expression: Apache-2.0
License-File: LICENSE
Keywords: animation,data structures,gui,visualization
Classifier: Development Status :: 3 - Alpha
Classifier: Intended Audience :: Developers
Classifier: License :: OSI Approved :: Apache Software License
Classifier: Programming Language :: Python :: 3
Classifier: Programming Language :: Python :: 3.11
Classifier: Programming Language :: Python :: 3.12
Classifier: Programming Language :: Python :: 3.13
Classifier: Topic :: Multimedia :: Graphics :: Presentation
Classifier: Topic :: Software Development :: Libraries :: Python Modules
Requires-Python: >=3.11
Provides-Extra: dev
Requires-Dist: invoke>=2.2.0; extra == 'dev'
Requires-Dist: mypy>=1.10.0; extra == 'dev'
Requires-Dist: pytest-cov>=4.1.0; extra == 'dev'
Requires-Dist: pytest>=8.0.0; extra == 'dev'
Requires-Dist: ruff>=0.4.0; extra == 'dev'
Provides-Extra: docs
Requires-Dist: myst-parser>=3.0.0; extra == 'docs'
Requires-Dist: sphinx-rtd-theme>=2.0.0; extra == 'docs'
Requires-Dist: sphinx>=7.0.0; extra == 'docs'
Provides-Extra: tutorial
Requires-Dist: fastapi>=0.110.0; extra == 'tutorial'
Requires-Dist: jinja2>=3.1.0; extra == 'tutorial'
Requires-Dist: pypubsub>=4.0.3; extra == 'tutorial'
Requires-Dist: uvicorn>=0.29.0; extra == 'tutorial'
Requires-Dist: wsproto>=1.2.0; extra == 'tutorial'
